{
    "data": [
        {
            "file_name": "dslr_images_undistorted/DSC_0614.JPG",
            "image_id": "1",
            "qw": -0.201163,
            "qx": -0.201805,
            "qy": 0.670565,
            "qz": -0.684945,
            "tx": -4.36094,
            "ty": -0.189141,
            "tz": 0.301486,
            "roll": 92.07088158660041,
            "pitch": -56.86760583098453,
            "yaw": -87.98339154704959,
            "WIDTH": 6215,
            "HEIGHT": 4147,
            "vfov": 62.321420303294495,
            "dataset": "terrains_test"
        },
        {
            "file_name": "dslr_images_undistorted/DSC_0615.JPG",
            "image_id": "2",
            "qw": -0.211181,
            "qx": -0.210143,
            "qy": 0.667119,
            "qz": -0.682784,
            "tx": -3.95373,
            "ty": -0.178339,
            "tz": 0.44228,
            "roll": 92.08524264792014,
            "pitch": -55.30971552795775,
            "yaw": -87.82664286176025,
            "WIDTH": 6215,
            "HEIGHT": 4147,
            "vfov": 62.321420303294495,
            "dataset": "terrains_test"
        },
        {
            "file_name": "dslr_images_undistorted/DSC_0616.JPG",
            "image_id": "3",
            "qw": -0.206013,
            "qx": -0.204011,
            "qy": 0.669199,
            "qz": -0.684186,
            "tx": -3.61016,
            "ty": -0.171534,
            "tz": 0.395669,
            "roll": 92.00856092710282,
            "pitch": -56.26919047907952,
            "yaw": -87.82192918928098,
            "WIDTH": 6215,
            "HEIGHT": 4147,
            "vfov": 62.321420303294495,
            "dataset": "terrains_test"
        },
        {
            "file_name": "dslr_images_undistorted/DSC_0617.JPG",
            "image_id": "4",
            "qw": -0.216302,
            "qx": -0.211873,
            "qy": 0.667311,
            "qz": -0.680455,
            "tx": -3.26039,
            "ty": -0.154865,
            "tz": 0.510997,
            "roll": 91.57001462885363,
            "pitch": -54.735289662492114,
            "yaw": -88.05341837953273,
            "WIDTH": 6215,
            "HEIGHT": 4147,
            "vfov": 62.321420303294495,
            "dataset": "terrains_test"
        },
        {
            "file_name": "dslr_images_undistorted/DSC_0618.JPG",
            "image_id": "5",
            "qw": -0.219395,
            "qx": -0.215567,
            "qy": 0.666914,
            "qz": -0.678692,
            "tx": -2.90366,
            "ty": -0.15706,
            "tz": 0.546442,
            "roll": 91.38809367834278,
            "pitch": -54.161386745859126,
            "yaw": -88.28591542639286,
            "WIDTH": 6215,
            "HEIGHT": 4147,
            "vfov": 62.321420303294495,
            "dataset": "terrains_test"
        },
        {
            "file_name": "dslr_images_undistorted/DSC_0619.JPG",
            "image_id": "6",
            "qw": -0.220716,
            "qx": -0.218369,
            "qy": 0.66503,
            "qz": -0.679217,
            "tx": -2.61258,
            "ty": -0.162419,
            "tz": 0.538698,
            "roll": 91.75056821013334,
            "pitch": -53.80417293905312,
            "yaw": -88.04935984196425,
            "WIDTH": 6215,
            "HEIGHT": 4147,
            "vfov": 62.321420303294495,
            "dataset": "terrains_test"
        },
        {
            "file_name": "dslr_images_undistorted/DSC_0620.JPG",
            "image_id": "7",
            "qw": -0.216392,
            "qx": -0.211809,
            "qy": 0.66855,
            "qz": -0.67923,
            "tx": -2.29876,
            "ty": -0.152552,
            "tz": 0.483541,
            "roll": 91.23392158493014,
            "pitch": -54.73893021269154,
            "yaw": -88.3764220239082,
            "WIDTH": 6215,
            "HEIGHT": 4147,
            "vfov": 62.321420303294495,
            "dataset": "terrains_test"
        },
        {
            "file_name": "dslr_images_undistorted/DSC_0622.JPG",
            "image_id": "8",
            "qw": -0.223428,
            "qx": -0.217197,
            "qy": 0.66589,
            "qz": -0.677862,
            "tx": -1.97398,
            "ty": -0.147445,
            "tz": 0.491759,
            "roll": 91.29069229716926,
            "pitch": -53.67853850919871,
            "yaw": -88.17794857796427,
            "WIDTH": 6215,
            "HEIGHT": 4147,
            "vfov": 62.321420303294495,
            "dataset": "terrains_test"
        },
        {
            "file_name": "dslr_images_undistorted/DSC_0623.JPG",
            "image_id": "9",
            "qw": -0.218907,
            "qx": -0.215513,
            "qy": 0.666783,
            "qz": -0.678995,
            "tx": -1.68812,
            "ty": -0.156028,
            "tz": 0.442515,
            "roll": 91.46572272395998,
            "pitch": -54.20649392281514,
            "yaw": -88.24528241449366,
            "WIDTH": 6215,
            "HEIGHT": 4147,
            "vfov": 62.321420303294495,
            "dataset": "terrains_test"
        },
        {
            "file_name": "dslr_images_undistorted/DSC_0624.JPG",
            "image_id": "10",
            "qw": -0.212874,
            "qx": -0.213383,
            "qy": 0.667054,
            "qz": -0.681316,
            "tx": -1.38215,
            "ty": -0.164711,
            "tz": 0.415355,
            "roll": 91.93795547342904,
            "pitch": -54.89520539745045,
            "yaw": -88.10530201581629,
            "WIDTH": 6215,
            "HEIGHT": 4147,
            "vfov": 62.321420303294495,
            "dataset": "terrains_test"
        },
        {
            "file_name": "dslr_images_undistorted/DSC_0625.JPG",
            "image_id": "11",
            "qw": -0.217569,
            "qx": -0.217823,
            "qy": 0.664633,
            "qz": -0.680794,
            "tx": -1.07366,
            "ty": -0.162342,
            "tz": 0.433088,
            "roll": 92.13656133579022,
            "pitch": -54.1128126904389,
            "yaw": -87.88507213495684,
            "WIDTH": 6215,
            "HEIGHT": 4147,
            "vfov": 62.321420303294495,
            "dataset": "terrains_test"
        },
        {
            "file_name": "dslr_images_undistorted/DSC_0626.JPG",
            "image_id": "12",
            "qw": -0.221339,
            "qx": -0.219017,
            "qy": 0.663738,
            "qz": -0.680068,
            "tx": -0.791632,
            "ty": -0.157447,
            "tz": 0.410311,
            "roll": 92.02475956619963,
            "pitch": -53.68951460347696,
            "yaw": -87.77723466865059,
            "WIDTH": 6215,
            "HEIGHT": 4147,
            "vfov": 62.321420303294495,
            "dataset": "terrains_test"
        },
        {
            "file_name": "dslr_images_undistorted/DSC_0627.JPG",
            "image_id": "13",
            "qw": -0.217968,
            "qx": -0.216319,
            "qy": 0.66604,
            "qz": -0.67977,
            "tx": -0.518046,
            "ty": -0.159613,
            "tz": 0.384728,
            "roll": 91.74060151014794,
            "pitch": -54.213966192441866,
            "yaw": -88.11899131033171,
            "WIDTH": 6215,
            "HEIGHT": 4147,
            "vfov": 62.321420303294495,
            "dataset": "terrains_test"
        },
        {
            "file_name": "dslr_images_undistorted/DSC_0628.JPG",
            "image_id": "14",
            "qw": -0.216224,
            "qx": -0.215816,
            "qy": 0.666812,
            "qz": -0.679729,
            "tx": -0.219454,
            "ty": -0.16063,
            "tz": 0.370716,
            "roll": 91.69514105131124,
            "pitch": -54.40725108206304,
            "yaw": -88.270137871015,
            "WIDTH": 6215,
            "HEIGHT": 4147,
            "vfov": 62.321420303294495,
            "dataset": "terrains_test"
        },
        {
            "file_name": "dslr_images_undistorted/DSC_0629.JPG",
            "image_id": "15",
            "qw": -0.216595,
            "qx": -0.215426,
            "qy": 0.666398,
            "qz": -0.680141,
            "tx": 0.10583,
            "ty": -0.15818,
            "tz": 0.371613,
            "roll": 91.77227755125553,
            "pitch": -54.40671245016506,
            "yaw": -88.12823962734267,
            "WIDTH": 6215,
            "HEIGHT": 4147,
            "vfov": 62.321420303294495,
            "dataset": "terrains_test"
        },
        {
            "file_name": "dslr_images_undistorted/DSC_0630.JPG",
            "image_id": "16",
            "qw": -0.224153,
            "qx": -0.220216,
            "qy": 0.664932,
            "qz": -0.677588,
            "tx": 0.418238,
            "ty": -0.157524,
            "tz": 0.379342,
            "roll": 91.46336865435174,
            "pitch": -53.357592718270524,
            "yaw": -88.20058743223768,
            "WIDTH": 6215,
            "HEIGHT": 4147,
            "vfov": 62.321420303294495,
            "dataset": "terrains_test"
        },
        {
            "file_name": "dslr_images_undistorted/DSC_0631.JPG",
            "image_id": "17",
            "qw": -0.227167,
            "qx": -0.221124,
            "qy": 0.665597,
            "qz": -0.675633,
            "tx": 0.714953,
            "ty": -0.161257,
            "tz": 0.383041,
            "roll": 91.0243322127809,
            "pitch": -53.02847045922838,
            "yaw": -88.45937147304168,
            "WIDTH": 6215,
            "HEIGHT": 4147,
            "vfov": 62.321420303294495,
            "dataset": "terrains_test"
        },
        {
            "file_name": "dslr_images_undistorted/DSC_0632.JPG",
            "image_id": "18",
            "qw": -0.226643,
            "qx": -0.222204,
            "qy": 0.663645,
            "qz": -0.677372,
            "tx": 1.01087,
            "ty": -0.154708,
            "tz": 0.409852,
            "roll": 91.56206129695667,
            "pitch": -52.972614840127434,
            "yaw": -88.05862205556842,
            "WIDTH": 6215,
            "HEIGHT": 4147,
            "vfov": 62.321420303294495,
            "dataset": "terrains_test"
        },
        {
            "file_name": "dslr_images_undistorted/DSC_0648.JPG",
            "image_id": "19",
            "qw": -0.626986,
            "qx": -0.625389,
            "qy": 0.325695,
            "qz": -0.33121,
            "tx": -0.480164,
            "ty": -0.189501,
            "tz": 1.11389,
            "roll": 90.11301661716395,
            "pitch": 34.643835029593134,
            "yaw": -89.60840069700411,
            "WIDTH": 6215,
            "HEIGHT": 4147,
            "vfov": 62.321420303294495,
            "dataset": "terrains_test"
        },
        {
            "file_name": "dslr_images_undistorted/DSC_0649.JPG",
            "image_id": "20",
            "qw": -0.628339,
            "qx": -0.626608,
            "qy": 0.325604,
            "qz": -0.326397,
            "tx": -0.136375,
            "ty": -0.188647,
            "tz": 1.11934,
            "roll": 89.88409072088325,
            "pitch": 35.09206163366126,
            "yaw": -89.81168041653343,
            "WIDTH": 6215,
            "HEIGHT": 4147,
            "vfov": 62.321420303294495,
            "dataset": "terrains_test"
        },
        {
            "file_name": "dslr_images_undistorted/DSC_0650.JPG",
            "image_id": "21",
            "qw": -0.629289,
            "qx": -0.629147,
            "qy": 0.321701,
            "qz": -0.323539,
            "tx": 0.17289,
            "ty": -0.190613,
            "tz": 1.10421,
            "roll": 90.07107363263063,
            "pitch": 35.708745579532625,
            "yaw": -89.90370784229493,
            "WIDTH": 6215,
            "HEIGHT": 4147,
            "vfov": 62.321420303294495,
            "dataset": "terrains_test"
        },
        {
            "file_name": "dslr_images_undistorted/DSC_0651.JPG",
            "image_id": "22",
            "qw": -0.626388,
            "qx": -0.625536,
            "qy": 0.326635,
            "qz": -0.331138,
            "tx": 0.418591,
            "ty": -0.185953,
            "tz": 1.09943,
            "roll": 90.13187020382058,
            "pitch": 34.56452312251493,
            "yaw": -89.71970176144757,
            "WIDTH": 6215,
            "HEIGHT": 4147,
            "vfov": 62.321420303294495,
            "dataset": "terrains_test"
        },
        {
            "file_name": "dslr_images_undistorted/DSC_0652.JPG",
            "image_id": "23",
            "qw": -0.624233,
            "qx": -0.623112,
            "qy": 0.331297,
            "qz": -0.335124,
            "tx": 0.650845,
            "ty": -0.185714,
            "tz": 1.09794,
            "roll": 90.0794113074416,
            "pitch": 33.77150881405739,
            "yaw": -89.72783213700131,
            "WIDTH": 6215,
            "HEIGHT": 4147,
            "vfov": 62.321420303294495,
            "dataset": "terrains_test"
        },
        {
            "file_name": "dslr_images_undistorted/DSC_0653.JPG",
            "image_id": "24",
            "qw": -0.626227,
            "qx": -0.627697,
            "qy": 0.325971,
            "qz": -0.327992,
            "tx": 1.01505,
            "ty": -0.19116,
            "tz": 1.08629,
            "roll": 90.2211370050417,
            "pitch": 34.91286918452961,
            "yaw": -90.03644531698227,
            "WIDTH": 6215,
            "HEIGHT": 4147,
            "vfov": 62.321420303294495,
            "dataset": "terrains_test"
        },
        {
            "file_name": "dslr_images_undistorted/DSC_0654.JPG",
            "image_id": "25",
            "qw": 0.320351,
            "qx": 0.315209,
            "qy": 0.630986,
            "qz": -0.632357,
            "tx": 0.58867,
            "ty": -0.194765,
            "tz": -0.859094,
            "roll": -89.89039422366106,
            "pitch": -36.5883540117753,
            "yaw": 89.64320311072203,
            "WIDTH": 6215,
            "HEIGHT": 4147,
            "vfov": 62.321420303294495,
            "dataset": "terrains_test"
        },
        {
            "file_name": "dslr_images_undistorted/DSC_0655.JPG",
            "image_id": "26",
            "qw": 0.339647,
            "qx": 0.333639,
            "qy": 0.620334,
            "qz": -0.623306,
            "tx": 0.216646,
            "ty": -0.199754,
            "tz": -0.863948,
            "roll": -89.97611915205623,
            "pitch": -33.139338405440746,
            "yaw": 89.4702956216624,
            "WIDTH": 6215,
            "HEIGHT": 4147,
            "vfov": 62.321420303294495,
            "dataset": "terrains_test"
        },
        {
            "file_name": "dslr_images_undistorted/DSC_0656.JPG",
            "image_id": "27",
            "qw": 0.324062,
            "qx": 0.318575,
            "qy": 0.627157,
            "qz": -0.632588,
            "tx": -0.105966,
            "ty": -0.204858,
            "tz": -0.920543,
            "roll": -90.23464336069748,
            "pitch": -35.943562047311794,
            "yaw": 89.26623982741069,
            "WIDTH": 6215,
            "HEIGHT": 4147,
            "vfov": 62.321420303294495,
            "dataset": "terrains_test"
        },
        {
            "file_name": "dslr_images_undistorted/DSC_0657.JPG",
            "image_id": "28",
            "qw": 0.337959,
            "qx": 0.332343,
            "qy": 0.619782,
            "qz": -0.625461,
            "tx": -0.358273,
            "ty": -0.206642,
            "tz": -0.941002,
            "roll": -90.22701534950852,
            "pitch": -33.412487718566915,
            "yaw": 89.25618444976689,
            "WIDTH": 6215,
            "HEIGHT": 4147,
            "vfov": 62.321420303294495,
            "dataset": "terrains_test"
        },
        {
            "file_name": "dslr_images_undistorted/DSC_0658.JPG",
            "image_id": "29",
            "qw": 0.337098,
            "qx": 0.332499,
            "qy": 0.619229,
            "qz": -0.62639,
            "tx": -0.746913,
            "ty": -0.208397,
            "tz": -1.00594,
            "roll": -90.40118282697642,
            "pitch": -33.47605313500653,
            "yaw": 89.175730992353,
            "WIDTH": 6215,
            "HEIGHT": 4147,
            "vfov": 62.321420303294495,
            "dataset": "terrains_test"
        },
        {
            "file_name": "dslr_images_undistorted/DSC_0659.JPG",
            "image_id": "30",
            "qw": 0.339253,
            "qx": 0.334283,
            "qy": 0.618417,
            "qz": -0.625078,
            "tx": -0.978304,
            "ty": -0.20918,
            "tz": -1.0185,
            "roll": -90.3376152162865,
            "pitch": -33.113874504025944,
            "yaw": 89.20438775452737,
            "WIDTH": 6215,
            "HEIGHT": 4147,
            "vfov": 62.321420303294495,
            "dataset": "terrains_test"
        },
        {
            "file_name": "dslr_images_undistorted/DSC_0660.JPG",
            "image_id": "31",
            "qw": 0.333825,
            "qx": 0.326542,
            "qy": 0.623456,
            "qz": -0.627084,
            "tx": -0.934307,
            "ty": -0.236074,
            "tz": -3.2552,
            "roll": -89.98109475533147,
            "pitch": -34.32611336376488,
            "yaw": 89.35154483314106,
            "WIDTH": 6215,
            "HEIGHT": 4147,
            "vfov": 62.321420303294495,
            "dataset": "terrains_test"
        },
        {
            "file_name": "dslr_images_undistorted/DSC_0661.JPG",
            "image_id": "32",
            "qw": 0.329666,
            "qx": 0.32076,
            "qy": 0.625094,
            "qz": -0.630627,
            "tx": -0.605591,
            "ty": -0.245545,
            "tz": -3.26375,
            "roll": -90.08103379106765,
            "pitch": -35.23386705787181,
            "yaw": 89.10625756305919,
            "WIDTH": 6215,
            "HEIGHT": 4147,
            "vfov": 62.321420303294495,
            "dataset": "terrains_test"
        },
        {
            "file_name": "dslr_images_undistorted/DSC_0662.JPG",
            "image_id": "33",
            "qw": 0.335092,
            "qx": 0.328465,
            "qy": 0.620551,
            "qz": -0.628283,
            "tx": -0.187224,
            "ty": -0.246769,
            "tz": -3.31192,
            "roll": -90.3635603378371,
            "pitch": -34.03034314160926,
            "yaw": 89.02835953806152,
            "WIDTH": 6215,
            "HEIGHT": 4147,
            "vfov": 62.321420303294495,
            "dataset": "terrains_test"
        },
        {
            "file_name": "dslr_images_undistorted/DSC_0663.JPG",
            "image_id": "34",
            "qw": 0.329789,
            "qx": 0.322536,
            "qy": 0.623294,
            "qz": -0.631439,
            "tx": 0.103829,
            "ty": -0.248604,
            "tz": -3.32045,
            "roll": -90.3841687911117,
            "pitch": -35.05805347906871,
            "yaw": 88.95344062813749,
            "WIDTH": 6215,
            "HEIGHT": 4147,
            "vfov": 62.321420303294495,
            "dataset": "terrains_test"
        },
        {
            "file_name": "dslr_images_undistorted/DSC_0664.JPG",
            "image_id": "35",
            "qw": 0.341456,
            "qx": 0.33247,
            "qy": 0.617697,
            "qz": -0.625557,
            "tx": 0.549543,
            "ty": -0.248324,
            "tz": -3.29485,
            "roll": -90.2540948432404,
            "pitch": -33.076738146347765,
            "yaw": 88.91767390336497,
            "WIDTH": 6215,
            "HEIGHT": 4147,
            "vfov": 62.321420303294495,
            "dataset": "terrains_test"
        },
        {
            "file_name": "dslr_images_undistorted/DSC_0665.JPG",
            "image_id": "36",
            "qw": 0.329846,
            "qx": 0.317361,
            "qy": 0.624403,
            "qz": -0.632933,
            "tx": 0.722932,
            "ty": -0.254031,
            "tz": -3.29567,
            "roll": -90.18618538431632,
            "pitch": -35.52444226428266,
            "yaw": 88.67598940749923,
            "WIDTH": 6215,
            "HEIGHT": 4147,
            "vfov": 62.321420303294495,
            "dataset": "terrains_test"
        },
        {
            "file_name": "dslr_images_undistorted/DSC_0666.JPG",
            "image_id": "37",
            "qw": -0.625574,
            "qx": -0.617561,
            "qy": 0.334657,
            "qz": -0.33953,
            "tx": -0.728648,
            "ty": -0.159552,
            "tz": 2.97467,
            "roll": 89.54364148435538,
            "pitch": 33.052538292710764,
            "yaw": -89.09445309609316,
            "WIDTH": 6215,
            "HEIGHT": 4147,
            "vfov": 62.321420303294495,
            "dataset": "terrains_test"
        },
        {
            "file_name": "dslr_images_undistorted/DSC_0667.JPG",
            "image_id": "38",
            "qw": -0.631346,
            "qx": -0.62234,
            "qy": 0.322822,
            "qz": -0.331482,
            "tx": -0.276735,
            "ty": -0.150611,
            "tz": 2.97154,
            "roll": 89.60718849539307,
            "pitch": 34.87617804086259,
            "yaw": -88.81564490475995,
            "WIDTH": 6215,
            "HEIGHT": 4147,
            "vfov": 62.321420303294495,
            "dataset": "terrains_test"
        },
        {
            "file_name": "dslr_images_undistorted/DSC_0668.JPG",
            "image_id": "39",
            "qw": -0.629288,
            "qx": -0.618792,
            "qy": 0.32488,
            "qz": -0.33992,
            "tx": 0.0486451,
            "ty": -0.130656,
            "tz": 2.9451,
            "roll": 89.7858874471345,
            "pitch": 33.91280498097636,
            "yaw": -88.40506760288683,
            "WIDTH": 6215,
            "HEIGHT": 4147,
            "vfov": 62.321420303294495,
            "dataset": "terrains_test"
        },
        {
            "file_name": "dslr_images_undistorted/DSC_0669.JPG",
            "image_id": "40",
            "qw": -0.633853,
            "qx": -0.6238,
            "qy": 0.316151,
            "qz": -0.330383,
            "tx": 0.474132,
            "ty": -0.131178,
            "tz": 2.92267,
            "roll": 89.75752544423202,
            "pitch": 35.58379034126932,
            "yaw": -88.46082638840562,
            "WIDTH": 6215,
            "HEIGHT": 4147,
            "vfov": 62.321420303294495,
            "dataset": "terrains_test"
        },
        {
            "file_name": "dslr_images_undistorted/DSC_0670.JPG",
            "image_id": "41",
            "qw": -0.631872,
            "qx": -0.621399,
            "qy": 0.321153,
            "qz": -0.333859,
            "tx": 0.80384,
            "ty": -0.13132,
            "tz": 2.92033,
            "roll": 89.66483487956448,
            "pitch": 34.80949263160635,
            "yaw": -88.50311449562841,
            "WIDTH": 6215,
            "HEIGHT": 4147,
            "vfov": 62.321420303294495,
            "dataset": "terrains_test"
        },
        {
            "file_name": "dslr_images_undistorted/DSC_0671.JPG",
            "image_id": "42",
            "qw": -0.634778,
            "qx": -0.623704,
            "qy": 0.315137,
            "qz": -0.329755,
            "tx": 1.12747,
            "ty": -0.120981,
            "tz": 2.92267,
            "roll": 89.6817150097121,
            "pitch": 35.731773025170256,
            "yaw": -88.35072729580526,
            "WIDTH": 6215,
            "HEIGHT": 4147,
            "vfov": 62.321420303294495,
            "dataset": "terrains_test"
        }
    ]
}